{
    "boxShadow": "none",
    "mobileBottomRow": 13,
    "widgetName": "Image1Copy1",
    "displayName": "Image",
    "iconSVG": "https://appcdn.appsmith.com/static/media/icon.69b0f0dd810281fbd6e34fc2c3f39344.svg",
    "topRow": 10,
    "bottomRow": 23,
    "parentRowSpace": 10,
    "type": "IMAGE_WIDGET",
    "hideCard": false,
    "mobileRightColumn": 37,
    "animateLoading": true,
    "parentColumnSpace": 1.83056640625,
    "dynamicTriggerPathList": [],
    "imageShape": "RECTANGLE",
    "leftColumn": 43,
    "dynamicBindingPathList": [{"key": "borderRadius"}],
    "defaultImage": "",
    "key": "gap9k4xhj2",
    "image": "https://assets.learnvern.com/course/icons/33290.svg",
    "isDeprecated": false,
    "rightColumn": 58,
    "objectFit": "cover",
    "widgetId": "7nvg1g0cii",
    "isVisible": true,
    "version": 1,
    "parentId": "7k9xiafsot",
    "tags": ["Media"],
    "renderMode": "CANVAS",
    "isLoading": false,
    "mobileTopRow": 1,
    "maxZoomLevel": 1,
    "enableDownload": false,
    "borderRadius": "{{appsmith.theme.borderRadius.appBorderRadius}}",
    "mobileLeftColumn": 25,
    "enableRotation": false
}